{
  "area": 9.5904,
  "cell_footprint": "sky130_fd_sc_lp__nor4",
  "cell_leakage_power": 0.0,
  "dont_touch": "true",
  "dont_use": "true",
  "pg_pin,VGND": {
    "pg_type": "primary_ground",
    "voltage_name": "VGND"
  },
  "pg_pin,VNB": {
    "pg_type": "primary_ground",
    "voltage_name": "VNB"
  },
  "pg_pin,VPB": {
    "pg_type": "primary_power",
    "voltage_name": "VPB"
  },
  "pg_pin,VPWR": {
    "pg_type": "primary_power",
    "voltage_name": "VPWR"
  },
  "pin,A": {
    "capacitance": 0.00184,
    "clock": "false",
    "direction": "input",
    "internal_power": {
      "fall_power,hidden_pwr_template13": {
        "index_1": [
          0.001,
          0.00617,
          0.01028,
          0.01851,
          0.03085,
          0.05553,
          0.09255,
          0.16659,
          0.27765,
          0.49977,
          0.83295,
          1.16647,
          1.5
        ],
        "values": [
          0.00338,
          0.00343,
          0.00371,
          0.00297,
          0.00331,
          0.00331,
          0.00337,
          0.00337,
          0.00338,
          0.00366,
          0.00366,
          0.00393,
          0.00393
        ]
      },
      "rise_power,hidden_pwr_template13": {
        "index_1": [
          0.001,
          0.00617,
          0.01028,
          0.01851,
          0.03085,
          0.05553,
          0.09255,
          0.16659,
          0.27765,
          0.49977,
          0.83295,
          1.16647,
          1.5
        ],
        "values": [
          0.00126,
          0.00123,
          0.00192,
          0.00111,
          0.00114,
          0.00131,
          0.00133,
          0.00135,
          0.00136,
          0.00149,
          0.00149,
          0.0016,
          0.00159
        ]
      }
    },
    "max_transition": 1.0,
    "related_ground_pin": "VGND",
    "related_power_pin": "VPWR"
  },
  "pin,B": {
    "capacitance": 0.00173,
    "clock": "false",
    "direction": "input",
    "internal_power": {
      "fall_power,hidden_pwr_template13": {
        "index_1": [
          0.001,
          0.00617,
          0.01028,
          0.01851,
          0.03085,
          0.05553,
          0.09255,
          0.16659,
          0.27765,
          0.49977,
          0.83295,
          1.16647,
          1.5
        ],
        "values": [
          0.00195,
          0.00197,
          0.00256,
          0.00197,
          0.00202,
          0.00201,
          0.00199,
          0.002,
          0.002,
          0.00217,
          0.00217,
          0.00233,
          0.00233
        ]
      },
      "rise_power,hidden_pwr_template13": {
        "index_1": [
          0.001,
          0.00617,
          0.01028,
          0.01851,
          0.03085,
          0.05553,
          0.09255,
          0.16659,
          0.27765,
          0.49977,
          0.83295,
          1.16647,
          1.5
        ],
        "values": [
          0.00133,
          0.0013,
          0.00174,
          0.00132,
          0.00126,
          0.00134,
          0.00136,
          0.00138,
          0.0014,
          0.00151,
          0.00152,
          0.00163,
          0.00164
        ]
      }
    },
    "max_transition": 1.0,
    "related_ground_pin": "VGND",
    "related_power_pin": "VPWR"
  },
  "pin,C": {
    "capacitance": 0.00161,
    "clock": "false",
    "direction": "input",
    "internal_power": {
      "fall_power,hidden_pwr_template13": {
        "index_1": [
          0.001,
          0.00617,
          0.01028,
          0.01851,
          0.03085,
          0.05553,
          0.09255,
          0.16659,
          0.27765,
          0.49977,
          0.83295,
          1.16647,
          1.5
        ],
        "values": [
          0.00154,
          0.00124,
          0.00156,
          0.00132,
          0.00128,
          0.00133,
          0.00133,
          0.00135,
          0.00135,
          0.00148,
          0.00148,
          0.00159,
          0.00158
        ]
      },
      "rise_power,hidden_pwr_template13": {
        "index_1": [
          0.001,
          0.00617,
          0.01028,
          0.01851,
          0.03085,
          0.05553,
          0.09255,
          0.16659,
          0.27765,
          0.49977,
          0.83295,
          1.16647,
          1.5
        ],
        "values": [
          0.00216,
          0.00208,
          0.00263,
          0.00182,
          0.00213,
          0.002,
          0.00205,
          0.00207,
          0.00207,
          0.00224,
          0.00225,
          0.00241,
          0.00241
        ]
      }
    },
    "max_transition": 1.0,
    "related_ground_pin": "VGND",
    "related_power_pin": "VPWR"
  },
  "pin,D": {
    "capacitance": 0.00152,
    "clock": "false",
    "direction": "input",
    "internal_power": {
      "fall_power,hidden_pwr_template13": {
        "index_1": [
          0.001,
          0.00617,
          0.01028,
          0.01851,
          0.03085,
          0.05553,
          0.09255,
          0.16659,
          0.27765,
          0.49977,
          0.83295,
          1.16647,
          1.5
        ],
        "values": [
          0.00131,
          0.00137,
          0.00121,
          0.00132,
          0.00136,
          0.00143,
          0.00146,
          0.00149,
          0.00151,
          0.00165,
          0.00166,
          0.00178,
          0.00178
        ]
      },
      "rise_power,hidden_pwr_template13": {
        "index_1": [
          0.001,
          0.00617,
          0.01028,
          0.01851,
          0.03085,
          0.05553,
          0.09255,
          0.16659,
          0.27765,
          0.49977,
          0.83295,
          1.16647,
          1.5
        ],
        "values": [
          0.00344,
          0.00342,
          0.00275,
          0.00331,
          0.00344,
          0.00343,
          0.00341,
          0.00342,
          0.00342,
          0.0037,
          0.0037,
          0.00399,
          0.00399
        ]
      }
    },
    "max_transition": 1.0,
    "related_ground_pin": "VGND",
    "related_power_pin": "VPWR"
  },
  "pin,Y": {
    "direction": "output",
    "function": "(!A&!B&!C&!D)",
    "internal_power": [
      {
        "fall_power,pwr_template13x7": {
          "index_1": [
            0.001,
            0.00617,
            0.01028,
            0.01851,
            0.03085,
            0.05553,
            0.09255,
            0.16659,
            0.27765,
            0.49977,
            0.83295,
            1.16647,
            1.5
          ],
          "index_2": [
            0.0,
            0.0096,
            0.01152,
            0.01382,
            0.01658,
            0.01989,
            0.02387
          ],
          "values": [
            [
              0.00214,
              -0.00951,
              -0.01185,
              -0.01465,
              -0.018,
              -0.02203,
              -0.02687
            ],
            [
              0.00217,
              -0.00948,
              -0.01181,
              -0.01461,
              -0.01797,
              -0.02199,
              -0.02683
            ],
            [
              0.00224,
              -0.00943,
              -0.01176,
              -0.01456,
              -0.01792,
              -0.02195,
              -0.02678
            ],
            [
              0.00226,
              -0.00941,
              -0.01176,
              -0.01454,
              -0.01791,
              -0.02192,
              -0.02678
            ],
            [
              0.00228,
              -0.0094,
              -0.01173,
              -0.01452,
              -0.01787,
              -0.02191,
              -0.02675
            ],
            [
              0.00232,
              -0.00935,
              -0.01169,
              -0.01449,
              -0.01785,
              -0.02187,
              -0.02672
            ],
            [
              0.00237,
              -0.00933,
              -0.01167,
              -0.01447,
              -0.01783,
              -0.02185,
              -0.02669
            ],
            [
              0.00244,
              -0.0093,
              -0.01163,
              -0.01444,
              -0.0178,
              -0.02183,
              -0.02667
            ],
            [
              0.00252,
              -0.00926,
              -0.0116,
              -0.01441,
              -0.01777,
              -0.0218,
              -0.02664
            ],
            [
              0.00259,
              -0.00921,
              -0.01156,
              -0.01437,
              -0.01773,
              -0.02177,
              -0.02661
            ],
            [
              0.00265,
              -0.00916,
              -0.01151,
              -0.01432,
              -0.01769,
              -0.02173,
              -0.02659
            ],
            [
              0.00265,
              -0.00914,
              -0.01149,
              -0.0143,
              -0.01767,
              -0.02171,
              -0.02656
            ],
            [
              0.00263,
              -0.00912,
              -0.01147,
              -0.01428,
              -0.01765,
              -0.02169,
              -0.02656
            ]
          ]
        },
        "related_pin": "A",
        "rise_power,pwr_template13x7": {
          "index_1": [
            0.001,
            0.00617,
            0.01028,
            0.01851,
            0.03085,
            0.05553,
            0.09255,
            0.16659,
            0.27765,
            0.49977,
            0.83295,
            1.16647,
            1.5
          ],
          "index_2": [
            0.0,
            0.0096,
            0.01152,
            0.01382,
            0.01658,
            0.01989,
            0.02387
          ],
          "values": [
            [
              0.01229,
              0.02387,
              0.02618,
              0.02895,
              0.03227,
              0.03628,
              0.04112
            ],
            [
              0.0122,
              0.02388,
              0.0262,
              0.02897,
              0.0323,
              0.03632,
              0.04116
            ],
            [
              0.01217,
              0.0239,
              0.02621,
              0.02899,
              0.03232,
              0.03633,
              0.04117
            ],
            [
              0.01208,
              0.02386,
              0.02617,
              0.02896,
              0.0323,
              0.03631,
              0.04115
            ],
            [
              0.01201,
              0.0238,
              0.02613,
              0.02891,
              0.03226,
              0.03628,
              0.04112
            ],
            [
              0.01194,
              0.02373,
              0.02606,
              0.02885,
              0.03219,
              0.03622,
              0.04108
            ],
            [
              0.01188,
              0.02364,
              0.02597,
              0.02876,
              0.03212,
              0.03615,
              0.04102
            ],
            [
              0.01186,
              0.02355,
              0.02588,
              0.02867,
              0.03203,
              0.03606,
              0.04092
            ],
            [
              0.01183,
              0.02349,
              0.02581,
              0.0286,
              0.03196,
              0.03601,
              0.04085
            ],
            [
              0.0118,
              0.02343,
              0.02575,
              0.02853,
              0.03187,
              0.03589,
              0.04075
            ],
            [
              0.01178,
              0.0234,
              0.02572,
              0.02849,
              0.03184,
              0.03585,
              0.04071
            ],
            [
              0.01179,
              0.02338,
              0.02569,
              0.02847,
              0.03181,
              0.03583,
              0.04066
            ],
            [
              0.01178,
              0.02337,
              0.02568,
              0.02847,
              0.03181,
              0.03582,
              0.04066
            ]
          ]
        },
        "when": "(!B&!C&!D)"
      },
      {
        "fall_power,pwr_template13x7": {
          "index_1": [
            0.001,
            0.00617,
            0.01028,
            0.01851,
            0.03085,
            0.05553,
            0.09255,
            0.16659,
            0.27765,
            0.49977,
            0.83295,
            1.16647,
            1.5
          ],
          "index_2": [
            0.0,
            0.0096,
            0.01152,
            0.01382,
            0.01658,
            0.01989,
            0.02387
          ],
          "values": [
            [
              0.00162,
              -0.01005,
              -0.01239,
              -0.01518,
              -0.01854,
              -0.02257,
              -0.02741
            ],
            [
              0.00168,
              -0.00998,
              -0.01232,
              -0.01511,
              -0.01847,
              -0.0225,
              -0.02734
            ],
            [
              0.00172,
              -0.00995,
              -0.01229,
              -0.01508,
              -0.01844,
              -0.02247,
              -0.02731
            ],
            [
              0.00174,
              -0.00994,
              -0.01229,
              -0.01507,
              -0.01843,
              -0.02247,
              -0.02732
            ],
            [
              0.00175,
              -0.00994,
              -0.01227,
              -0.01506,
              -0.01842,
              -0.02244,
              -0.02729
            ],
            [
              0.00178,
              -0.00991,
              -0.01225,
              -0.01504,
              -0.0184,
              -0.02243,
              -0.02727
            ],
            [
              0.00182,
              -0.00989,
              -0.01223,
              -0.01503,
              -0.01838,
              -0.02241,
              -0.02726
            ],
            [
              0.00189,
              -0.00986,
              -0.0122,
              -0.015,
              -0.01836,
              -0.02239,
              -0.02724
            ],
            [
              0.00196,
              -0.00983,
              -0.01217,
              -0.01498,
              -0.01834,
              -0.02237,
              -0.02722
            ],
            [
              0.00204,
              -0.00979,
              -0.01214,
              -0.01495,
              -0.01831,
              -0.02235,
              -0.0272
            ],
            [
              0.00206,
              -0.00974,
              -0.01209,
              -0.0149,
              -0.01827,
              -0.02231,
              -0.02717
            ],
            [
              0.00207,
              -0.00972,
              -0.01207,
              -0.01488,
              -0.01825,
              -0.02229,
              -0.02715
            ],
            [
              0.00204,
              -0.00971,
              -0.01206,
              -0.01487,
              -0.01824,
              -0.02228,
              -0.02714
            ]
          ]
        },
        "related_pin": "B",
        "rise_power,pwr_template13x7": {
          "index_1": [
            0.001,
            0.00617,
            0.01028,
            0.01851,
            0.03085,
            0.05553,
            0.09255,
            0.16659,
            0.27765,
            0.49977,
            0.83295,
            1.16647,
            1.5
          ],
          "index_2": [
            0.0,
            0.0096,
            0.01152,
            0.01382,
            0.01658,
            0.01989,
            0.02387
          ],
          "values": [
            [
              0.01017,
              0.02172,
              0.02403,
              0.0268,
              0.03013,
              0.03413,
              0.03899
            ],
            [
              0.01011,
              0.02175,
              0.02407,
              0.02684,
              0.03017,
              0.03417,
              0.039
            ],
            [
              0.01011,
              0.02178,
              0.0241,
              0.02687,
              0.03021,
              0.03421,
              0.03904
            ],
            [
              0.01004,
              0.02174,
              0.02405,
              0.02683,
              0.0302,
              0.03418,
              0.03901
            ],
            [
              0.00998,
              0.02171,
              0.02403,
              0.02682,
              0.03016,
              0.03417,
              0.03901
            ],
            [
              0.00993,
              0.02164,
              0.02397,
              0.02675,
              0.0301,
              0.03412,
              0.03898
            ],
            [
              0.00988,
              0.02158,
              0.0239,
              0.0267,
              0.03004,
              0.03407,
              0.03893
            ],
            [
              0.00986,
              0.02151,
              0.02384,
              0.02663,
              0.03,
              0.034,
              0.03887
            ],
            [
              0.00984,
              0.02146,
              0.02379,
              0.02657,
              0.02991,
              0.03395,
              0.0388
            ],
            [
              0.00982,
              0.02143,
              0.02375,
              0.02652,
              0.02986,
              0.03388,
              0.03873
            ],
            [
              0.0098,
              0.0214,
              0.02372,
              0.0265,
              0.02983,
              0.03385,
              0.03871
            ],
            [
              0.00981,
              0.02138,
              0.0237,
              0.02647,
              0.02981,
              0.03382,
              0.03867
            ],
            [
              0.00981,
              0.02137,
              0.02369,
              0.02646,
              0.0298,
              0.03382,
              0.03868
            ]
          ]
        },
        "when": "(!A&!C&!D)"
      },
      {
        "fall_power,pwr_template13x7": {
          "index_1": [
            0.001,
            0.00617,
            0.01028,
            0.01851,
            0.03085,
            0.05553,
            0.09255,
            0.16659,
            0.27765,
            0.49977,
            0.83295,
            1.16647,
            1.5
          ],
          "index_2": [
            0.0,
            0.0096,
            0.01152,
            0.01382,
            0.01658,
            0.01989,
            0.02387
          ],
          "values": [
            [
              0.00109,
              -0.01057,
              -0.0129,
              -0.0157,
              -0.01906,
              -0.02309,
              -0.02793
            ],
            [
              0.00116,
              -0.01051,
              -0.01285,
              -0.01565,
              -0.019,
              -0.02303,
              -0.02788
            ],
            [
              0.0012,
              -0.01048,
              -0.01282,
              -0.01562,
              -0.01897,
              -0.023,
              -0.02785
            ],
            [
              0.00121,
              -0.01048,
              -0.01282,
              -0.01562,
              -0.01898,
              -0.023,
              -0.02786
            ],
            [
              0.00122,
              -0.01049,
              -0.01282,
              -0.01562,
              -0.01897,
              -0.02301,
              -0.02785
            ],
            [
              0.00125,
              -0.01048,
              -0.01282,
              -0.01562,
              -0.01898,
              -0.02301,
              -0.02785
            ],
            [
              0.00129,
              -0.01048,
              -0.01282,
              -0.01562,
              -0.01898,
              -0.02301,
              -0.02785
            ],
            [
              0.00135,
              -0.01046,
              -0.0128,
              -0.0156,
              -0.01897,
              -0.023,
              -0.02785
            ],
            [
              0.00142,
              -0.01043,
              -0.01278,
              -0.01558,
              -0.01895,
              -0.02298,
              -0.02783
            ],
            [
              0.0015,
              -0.01038,
              -0.01273,
              -0.01556,
              -0.01893,
              -0.02297,
              -0.02781
            ],
            [
              0.00153,
              -0.01033,
              -0.01268,
              -0.0155,
              -0.01888,
              -0.02292,
              -0.02778
            ],
            [
              0.00153,
              -0.0103,
              -0.01266,
              -0.01548,
              -0.01885,
              -0.0229,
              -0.02776
            ],
            [
              0.00149,
              -0.01028,
              -0.01264,
              -0.01545,
              -0.01883,
              -0.02288,
              -0.02774
            ]
          ]
        },
        "related_pin": "C",
        "rise_power,pwr_template13x7": {
          "index_1": [
            0.001,
            0.00617,
            0.01028,
            0.01851,
            0.03085,
            0.05553,
            0.09255,
            0.16659,
            0.27765,
            0.49977,
            0.83295,
            1.16647,
            1.5
          ],
          "index_2": [
            0.0,
            0.0096,
            0.01152,
            0.01382,
            0.01658,
            0.01989,
            0.02387
          ],
          "values": [
            [
              0.00826,
              0.01981,
              0.02212,
              0.02489,
              0.02823,
              0.03223,
              0.03705
            ],
            [
              0.0082,
              0.01984,
              0.02215,
              0.02492,
              0.02826,
              0.03226,
              0.03708
            ],
            [
              0.0082,
              0.01987,
              0.02218,
              0.02495,
              0.02829,
              0.03232,
              0.03713
            ],
            [
              0.00811,
              0.01984,
              0.02216,
              0.02493,
              0.02827,
              0.03228,
              0.03713
            ],
            [
              0.00806,
              0.01978,
              0.02211,
              0.02489,
              0.02822,
              0.03225,
              0.0371
            ],
            [
              0.008,
              0.01974,
              0.02206,
              0.02484,
              0.0282,
              0.03222,
              0.03705
            ],
            [
              0.00797,
              0.01968,
              0.02201,
              0.02479,
              0.02815,
              0.03217,
              0.03702
            ],
            [
              0.00795,
              0.01961,
              0.02194,
              0.02472,
              0.02808,
              0.0321,
              0.03696
            ],
            [
              0.00793,
              0.01956,
              0.02188,
              0.02467,
              0.028,
              0.03203,
              0.0369
            ],
            [
              0.00791,
              0.01952,
              0.02183,
              0.02461,
              0.02795,
              0.03197,
              0.03682
            ],
            [
              0.00789,
              0.01949,
              0.0218,
              0.02458,
              0.02792,
              0.03194,
              0.03679
            ],
            [
              0.0079,
              0.01947,
              0.02178,
              0.02456,
              0.0279,
              0.03191,
              0.03674
            ],
            [
              0.0079,
              0.01946,
              0.02177,
              0.02454,
              0.02788,
              0.03189,
              0.03674
            ]
          ]
        },
        "when": "(!A&!B&!D)"
      },
      {
        "fall_power,pwr_template13x7": {
          "index_1": [
            0.001,
            0.00617,
            0.01028,
            0.01851,
            0.03085,
            0.05553,
            0.09255,
            0.16659,
            0.27765,
            0.49977,
            0.83295,
            1.16647,
            1.5
          ],
          "index_2": [
            0.0,
            0.0096,
            0.01152,
            0.01382,
            0.01658,
            0.01989,
            0.02387
          ],
          "values": [
            [
              0.00049,
              -0.01117,
              -0.0135,
              -0.01631,
              -0.01967,
              -0.0237,
              -0.02854
            ],
            [
              0.00053,
              -0.01116,
              -0.0135,
              -0.0163,
              -0.01966,
              -0.02369,
              -0.02854
            ],
            [
              0.00058,
              -0.01114,
              -0.01348,
              -0.01628,
              -0.01964,
              -0.02367,
              -0.02855
            ],
            [
              0.00059,
              -0.01116,
              -0.01349,
              -0.01629,
              -0.01967,
              -0.0237,
              -0.02854
            ],
            [
              0.0006,
              -0.01116,
              -0.01351,
              -0.01632,
              -0.01967,
              -0.02371,
              -0.02855
            ],
            [
              0.00064,
              -0.01117,
              -0.01351,
              -0.01632,
              -0.01968,
              -0.02371,
              -0.02856
            ],
            [
              0.00069,
              -0.01117,
              -0.01351,
              -0.01632,
              -0.01968,
              -0.02371,
              -0.02856
            ],
            [
              0.00076,
              -0.01115,
              -0.0135,
              -0.01631,
              -0.01968,
              -0.02371,
              -0.02856
            ],
            [
              0.00083,
              -0.01112,
              -0.01347,
              -0.01629,
              -0.01966,
              -0.0237,
              -0.02855
            ],
            [
              0.00089,
              -0.01107,
              -0.01342,
              -0.01624,
              -0.01962,
              -0.02366,
              -0.02852
            ],
            [
              0.0009,
              -0.01101,
              -0.01337,
              -0.01619,
              -0.01957,
              -0.02362,
              -0.02848
            ],
            [
              0.00088,
              -0.01097,
              -0.01333,
              -0.01615,
              -0.01954,
              -0.02359,
              -0.02846
            ],
            [
              0.00083,
              -0.01095,
              -0.01331,
              -0.01613,
              -0.01952,
              -0.02357,
              -0.02844
            ]
          ]
        },
        "related_pin": "D",
        "rise_power,pwr_template13x7": {
          "index_1": [
            0.001,
            0.00617,
            0.01028,
            0.01851,
            0.03085,
            0.05553,
            0.09255,
            0.16659,
            0.27765,
            0.49977,
            0.83295,
            1.16647,
            1.5
          ],
          "index_2": [
            0.0,
            0.0096,
            0.01152,
            0.01382,
            0.01658,
            0.01989,
            0.02387
          ],
          "values": [
            [
              0.00624,
              0.01783,
              0.02014,
              0.0229,
              0.02624,
              0.03024,
              0.03509
            ],
            [
              0.00618,
              0.01784,
              0.02016,
              0.02293,
              0.02626,
              0.03027,
              0.03511
            ],
            [
              0.00615,
              0.01786,
              0.02018,
              0.02294,
              0.02628,
              0.03028,
              0.03512
            ],
            [
              0.00608,
              0.01783,
              0.02015,
              0.02293,
              0.02625,
              0.03028,
              0.03511
            ],
            [
              0.00601,
              0.01779,
              0.02011,
              0.02289,
              0.02623,
              0.03024,
              0.03508
            ],
            [
              0.00594,
              0.01772,
              0.02005,
              0.02283,
              0.02618,
              0.0302,
              0.03507
            ],
            [
              0.00591,
              0.01765,
              0.01998,
              0.02277,
              0.02611,
              0.03015,
              0.035
            ],
            [
              0.00588,
              0.01756,
              0.01989,
              0.02268,
              0.02604,
              0.03007,
              0.03492
            ],
            [
              0.00586,
              0.0175,
              0.01983,
              0.02262,
              0.02596,
              0.02999,
              0.03486
            ],
            [
              0.00585,
              0.01746,
              0.01978,
              0.02256,
              0.0259,
              0.02991,
              0.03476
            ],
            [
              0.00589,
              0.01744,
              0.01975,
              0.02252,
              0.02587,
              0.02987,
              0.03473
            ],
            [
              0.00595,
              0.01744,
              0.01975,
              0.02252,
              0.02585,
              0.02985,
              0.0347
            ],
            [
              0.00599,
              0.01745,
              0.01976,
              0.02253,
              0.02589,
              0.02986,
              0.03471
            ]
          ]
        },
        "when": "(!A&!B&!C)"
      }
    ],
    "max_capacitance": 0.02387,
    "max_transition": 1.0,
    "related_ground_pin": "VGND",
    "related_power_pin": "VPWR",
    "timing": [
      {
        "cell_fall,delay_template13x7": {
          "index_1": [
            0.001,
            0.00617,
            0.01028,
            0.01851,
            0.03085,
            0.05553,
            0.09255,
            0.16659,
            0.27765,
            0.49977,
            0.83295,
            1.16647,
            1.5
          ],
          "index_2": [
            0.0,
            0.0096,
            0.01152,
            0.01382,
            0.01658,
            0.01989,
            0.02387
          ],
          "values": [
            [
              0.01481,
              0.06303,
              0.07224,
              0.08316,
              0.09616,
              0.11168,
              0.13025
            ],
            [
              0.01684,
              0.06493,
              0.07412,
              0.08504,
              0.09803,
              0.11355,
              0.1321
            ],
            [
              0.01852,
              0.06652,
              0.0757,
              0.08661,
              0.09962,
              0.11512,
              0.13365
            ],
            [
              0.02196,
              0.06969,
              0.07883,
              0.08976,
              0.10272,
              0.11815,
              0.13669
            ],
            [
              0.02732,
              0.07445,
              0.08359,
              0.09455,
              0.10746,
              0.12295,
              0.14147
            ],
            [
              0.0365,
              0.08421,
              0.0933,
              0.10414,
              0.11707,
              0.13251,
              0.15102
            ],
            [
              0.04684,
              0.09917,
              0.10819,
              0.11894,
              0.13182,
              0.14722,
              0.1657
            ],
            [
              0.06203,
              0.12898,
              0.1383,
              0.14885,
              0.16151,
              0.17674,
              0.19506
            ],
            [
              0.07816,
              0.16497,
              0.17697,
              0.19031,
              0.20513,
              0.22165,
              0.24003
            ],
            [
              0.09874,
              0.21719,
              0.23347,
              0.25155,
              0.27164,
              0.29385,
              0.31844
            ],
            [
              0.11614,
              0.27275,
              0.29418,
              0.31798,
              0.34427,
              0.37328,
              0.40537
            ],
            [
              0.12424,
              0.31364,
              0.33944,
              0.36804,
              0.39954,
              0.43444,
              0.47294
            ],
            [
              0.1265,
              0.3461,
              0.3758,
              0.4087,
              0.445,
              0.485,
              0.5286
            ]
          ]
        },
        "cell_rise,delay_template13x7": {
          "index_1": [
            0.001,
            0.00617,
            0.01028,
            0.01851,
            0.03085,
            0.05553,
            0.09255,
            0.16659,
            0.27765,
            0.49977,
            0.83295,
            1.16647,
            1.5
          ],
          "index_2": [
            0.0,
            0.0096,
            0.01152,
            0.01382,
            0.01658,
            0.01989,
            0.02387
          ],
          "values": [
            [
              0.27074,
              0.93557,
              1.06787,
              1.22617,
              1.41507,
              1.64387,
              1.91857
            ],
            [
              0.26558,
              0.93542,
              1.06886,
              1.22626,
              1.41786,
              1.64586,
              1.91946
            ],
            [
              0.26368,
              0.93692,
              1.06883,
              1.22873,
              1.41923,
              1.64693,
              1.92023
            ],
            [
              0.26322,
              0.93907,
              1.07117,
              1.23138,
              1.42207,
              1.64997,
              1.92348
            ],
            [
              0.26572,
              0.94273,
              1.07509,
              1.23549,
              1.42649,
              1.65459,
              1.92839
            ],
            [
              0.27433,
              0.9509,
              1.08452,
              1.24392,
              1.43422,
              1.66252,
              1.93932
            ],
            [
              0.28915,
              0.96347,
              1.09698,
              1.25588,
              1.44778,
              1.67778,
              1.95278
            ],
            [
              0.31811,
              0.98877,
              1.12227,
              1.28318,
              1.47457,
              1.70328,
              1.97747
            ],
            [
              0.36011,
              1.02913,
              1.16182,
              1.32232,
              1.51382,
              1.74283,
              2.01722
            ],
            [
              0.439,
              1.10723,
              1.23913,
              1.39952,
              1.58952,
              1.81773,
              2.09463
            ],
            [
              0.53858,
              1.21938,
              1.35158,
              1.51048,
              1.70278,
              1.93088,
              2.20437
            ],
            [
              0.62854,
              1.32954,
              1.46234,
              1.62124,
              1.81234,
              2.04144,
              2.31494
            ],
            [
              0.7124,
              1.4389,
              1.5716,
              1.7305,
              1.9219,
              2.1499,
              2.4243
            ]
          ]
        },
        "fall_transition,delay_template13x7": {
          "index_1": [
            0.001,
            0.00617,
            0.01028,
            0.01851,
            0.03085,
            0.05553,
            0.09255,
            0.16659,
            0.27765,
            0.49977,
            0.83295,
            1.16647,
            1.5
          ],
          "index_2": [
            0.0,
            0.0096,
            0.01152,
            0.01382,
            0.01658,
            0.01989,
            0.02387
          ],
          "values": [
            [
              0.01572,
              0.07711,
              0.08886,
              0.10288,
              0.11976,
              0.13987,
              0.16398
            ],
            [
              0.01561,
              0.077,
              0.08874,
              0.10284,
              0.11967,
              0.13967,
              0.16386
            ],
            [
              0.01558,
              0.07688,
              0.08872,
              0.10279,
              0.11957,
              0.13973,
              0.16392
            ],
            [
              0.01555,
              0.07683,
              0.08863,
              0.10272,
              0.11955,
              0.13968,
              0.16378
            ],
            [
              0.01705,
              0.07661,
              0.08848,
              0.10253,
              0.11946,
              0.13947,
              0.1637
            ],
            [
              0.02233,
              0.07633,
              0.0882,
              0.10236,
              0.11925,
              0.13947,
              0.16372
            ],
            [
              0.0297,
              0.07821,
              0.08918,
              0.10258,
              0.11908,
              0.13924,
              0.16342
            ],
            [
              0.04175,
              0.08942,
              0.09868,
              0.11039,
              0.12501,
              0.14302,
              0.1654
            ],
            [
              0.05671,
              0.11458,
              0.12274,
              0.13202,
              0.14412,
              0.15962,
              0.17932
            ],
            [
              0.08211,
              0.15908,
              0.16985,
              0.18193,
              0.19527,
              0.21007,
              0.22669
            ],
            [
              0.11441,
              0.21459,
              0.22854,
              0.24404,
              0.26063,
              0.27951,
              0.30065
            ],
            [
              0.1439,
              0.2638,
              0.2802,
              0.2979,
              0.3179,
              0.3401,
              0.3647
            ],
            [
              0.1714,
              0.3085,
              0.327,
              0.3475,
              0.3697,
              0.3947,
              0.4234
            ]
          ]
        },
        "related_pin": "A",
        "rise_transition,delay_template13x7": {
          "index_1": [
            0.001,
            0.00617,
            0.01028,
            0.01851,
            0.03085,
            0.05553,
            0.09255,
            0.16659,
            0.27765,
            0.49977,
            0.83295,
            1.16647,
            1.5
          ],
          "index_2": [
            0.0,
            0.0096,
            0.01152,
            0.01382,
            0.01658,
            0.01989,
            0.02387
          ],
          "values": [
            [
              0.19519,
              1.06101,
              1.2344,
              1.44166,
              1.68879,
              1.98648,
              2.34496
            ],
            [
              0.19505,
              1.0601,
              1.23445,
              1.43998,
              1.68832,
              1.98779,
              2.34524
            ],
            [
              0.1953,
              1.06124,
              1.23329,
              1.43998,
              1.68981,
              1.98735,
              2.3447
            ],
            [
              0.19529,
              1.06125,
              1.23338,
              1.44002,
              1.68983,
              1.98737,
              2.34467
            ],
            [
              0.19528,
              1.06136,
              1.23336,
              1.44021,
              1.68985,
              1.98734,
              2.34473
            ],
            [
              0.19529,
              1.06074,
              1.23433,
              1.44162,
              1.68907,
              1.98569,
              2.34402
            ],
            [
              0.19506,
              1.06126,
              1.23448,
              1.44077,
              1.68947,
              1.98698,
              2.34575
            ],
            [
              0.19528,
              1.06058,
              1.23284,
              1.44071,
              1.69002,
              1.98715,
              2.3435
            ],
            [
              0.19551,
              1.06092,
              1.23309,
              1.44077,
              1.68958,
              1.988,
              2.3448
            ],
            [
              0.20397,
              1.061,
              1.233,
              1.4415,
              1.6888,
              1.9852,
              2.346
            ],
            [
              0.227,
              1.0611,
              1.2335,
              1.44,
              1.6898,
              1.9871,
              2.343
            ],
            [
              0.2448,
              1.0694,
              1.2373,
              1.4414,
              1.6894,
              1.9872,
              2.3435
            ],
            [
              0.2638,
              1.083,
              1.2487,
              1.4511,
              1.6939,
              1.9871,
              2.3434
            ]
          ]
        },
        "timing_sense": "negative_unate"
      },
      {
        "cell_fall,delay_template13x7": {
          "index_1": [
            0.001,
            0.00617,
            0.01028,
            0.01851,
            0.03085,
            0.05553,
            0.09255,
            0.16659,
            0.27765,
            0.49977,
            0.83295,
            1.16647,
            1.5
          ],
          "index_2": [
            0.0,
            0.0096,
            0.01152,
            0.01382,
            0.01658,
            0.01989,
            0.02387
          ],
          "values": [
            [
              0.01393,
              0.05978,
              0.06851,
              0.0789,
              0.09133,
              0.10615,
              0.12393
            ],
            [
              0.01601,
              0.06173,
              0.07046,
              0.08085,
              0.09326,
              0.10809,
              0.1259
            ],
            [
              0.01768,
              0.06333,
              0.07205,
              0.08244,
              0.09485,
              0.10969,
              0.1275
            ],
            [
              0.02112,
              0.06646,
              0.07515,
              0.08557,
              0.09799,
              0.11278,
              0.13054
            ],
            [
              0.02638,
              0.07118,
              0.07989,
              0.09029,
              0.10267,
              0.11753,
              0.13528
            ],
            [
              0.03503,
              0.08081,
              0.08941,
              0.09977,
              0.11214,
              0.12696,
              0.14475
            ],
            [
              0.04455,
              0.09538,
              0.10398,
              0.11431,
              0.12666,
              0.14145,
              0.15918
            ],
            [
              0.05795,
              0.12427,
              0.1335,
              0.1438,
              0.15599,
              0.17061,
              0.18821
            ],
            [
              0.07132,
              0.15779,
              0.16975,
              0.18318,
              0.19795,
              0.21433,
              0.23253
            ],
            [
              0.087,
              0.20578,
              0.22204,
              0.24,
              0.25999,
              0.2821,
              0.30661
            ],
            [
              0.09687,
              0.25565,
              0.27713,
              0.3009,
              0.32717,
              0.35607,
              0.38817
            ],
            [
              0.09804,
              0.29124,
              0.31724,
              0.34584,
              0.37744,
              0.41234,
              0.45084
            ],
            [
              0.0934,
              0.3183,
              0.3483,
              0.3813,
              0.4177,
              0.4577,
              0.5019
            ]
          ]
        },
        "cell_rise,delay_template13x7": {
          "index_1": [
            0.001,
            0.00617,
            0.01028,
            0.01851,
            0.03085,
            0.05553,
            0.09255,
            0.16659,
            0.27765,
            0.49977,
            0.83295,
            1.16647,
            1.5
          ],
          "index_2": [
            0.0,
            0.0096,
            0.01152,
            0.01382,
            0.01658,
            0.01989,
            0.02387
          ],
          "values": [
            [
              0.24542,
              0.90954,
              1.04177,
              1.19977,
              1.38867,
              1.61827,
              1.89207
            ],
            [
              0.24137,
              0.90904,
              1.04246,
              1.20116,
              1.39126,
              1.61856,
              1.89156
            ],
            [
              0.24018,
              0.91036,
              1.04243,
              1.20233,
              1.39253,
              1.62013,
              1.89283
            ],
            [
              0.24008,
              0.91204,
              1.04468,
              1.20467,
              1.39508,
              1.62277,
              1.89578
            ],
            [
              0.24284,
              0.91647,
              1.04839,
              1.20859,
              1.39939,
              1.62749,
              1.90059
            ],
            [
              0.25166,
              0.92485,
              1.05793,
              1.21622,
              1.40782,
              1.63732,
              1.91172
            ],
            [
              0.26724,
              0.93778,
              1.07198,
              1.23128,
              1.42128,
              1.65128,
              1.92578
            ],
            [
              0.29823,
              0.96637,
              1.10048,
              1.26008,
              1.45108,
              1.67917,
              1.95438
            ],
            [
              0.34341,
              1.01072,
              1.14302,
              1.30212,
              1.49432,
              1.72332,
              1.99673
            ],
            [
              0.43061,
              1.09803,
              1.23063,
              1.38862,
              1.57923,
              1.80953,
              2.08403
            ],
            [
              0.54448,
              1.22658,
              1.35998,
              1.51937,
              1.70948,
              1.93698,
              2.21347
            ],
            [
              0.64884,
              1.35634,
              1.48904,
              1.64834,
              1.83854,
              2.06644,
              2.34304
            ],
            [
              0.7459,
              1.4858,
              1.6185,
              1.7776,
              1.9678,
              2.1973,
              2.4726
            ]
          ]
        },
        "fall_transition,delay_template13x7": {
          "index_1": [
            0.001,
            0.00617,
            0.01028,
            0.01851,
            0.03085,
            0.05553,
            0.09255,
            0.16659,
            0.27765,
            0.49977,
            0.83295,
            1.16647,
            1.5
          ],
          "index_2": [
            0.0,
            0.0096,
            0.01152,
            0.01382,
            0.01658,
            0.01989,
            0.02387
          ],
          "values": [
            [
              0.01532,
              0.07271,
              0.08392,
              0.09743,
              0.11352,
              0.13287,
              0.15615
            ],
            [
              0.01517,
              0.07269,
              0.08389,
              0.09736,
              0.11351,
              0.13284,
              0.15626
            ],
            [
              0.01503,
              0.07262,
              0.08387,
              0.09733,
              0.11346,
              0.13285,
              0.15617
            ],
            [
              0.01507,
              0.07257,
              0.08386,
              0.09733,
              0.11351,
              0.13286,
              0.15624
            ],
            [
              0.01648,
              0.07246,
              0.08376,
              0.09722,
              0.11348,
              0.13279,
              0.15622
            ],
            [
              0.02154,
              0.07225,
              0.08354,
              0.09716,
              0.11344,
              0.13285,
              0.15617
            ],
            [
              0.02841,
              0.07466,
              0.08496,
              0.09777,
              0.11347,
              0.13266,
              0.15614
            ],
            [
              0.03971,
              0.08673,
              0.09553,
              0.10649,
              0.12025,
              0.13759,
              0.15883
            ],
            [
              0.05398,
              0.11239,
              0.12054,
              0.12944,
              0.14084,
              0.15546,
              0.17406
            ],
            [
              0.07847,
              0.15678,
              0.16729,
              0.17938,
              0.19276,
              0.20757,
              0.22401
            ],
            [
              0.11093,
              0.21157,
              0.22532,
              0.24056,
              0.25751,
              0.27654,
              0.29766
            ],
            [
              0.14058,
              0.2607,
              0.2769,
              0.2944,
              0.3143,
              0.3363,
              0.361
            ],
            [
              0.1685,
              0.3057,
              0.324,
              0.3439,
              0.3661,
              0.391,
              0.4186
            ]
          ]
        },
        "related_pin": "B",
        "rise_transition,delay_template13x7": {
          "index_1": [
            0.001,
            0.00617,
            0.01028,
            0.01851,
            0.03085,
            0.05553,
            0.09255,
            0.16659,
            0.27765,
            0.49977,
            0.83295,
            1.16647,
            1.5
          ],
          "index_2": [
            0.0,
            0.0096,
            0.01152,
            0.01382,
            0.01658,
            0.01989,
            0.02387
          ],
          "values": [
            [
              0.19527,
              1.06116,
              1.23448,
              1.44117,
              1.68842,
              1.98653,
              2.34589
            ],
            [
              0.19529,
              1.06067,
              1.23395,
              1.44119,
              1.68999,
              1.98701,
              2.34363
            ],
            [
              0.19527,
              1.061,
              1.23301,
              1.44054,
              1.68989,
              1.98731,
              2.34396
            ],
            [
              0.19525,
              1.06081,
              1.23293,
              1.44071,
              1.68991,
              1.98719,
              2.34381
            ],
            [
              0.19519,
              1.06152,
              1.23317,
              1.43986,
              1.68986,
              1.98748,
              2.34437
            ],
            [
              0.19533,
              1.06125,
              1.23445,
              1.44061,
              1.68945,
              1.98716,
              2.34564
            ],
            [
              0.19515,
              1.06036,
              1.23373,
              1.44147,
              1.6888,
              1.98653,
              2.34513
            ],
            [
              0.19537,
              1.06049,
              1.23366,
              1.44129,
              1.69005,
              1.98675,
              2.3458
            ],
            [
              0.19588,
              1.0611,
              1.23315,
              1.43958,
              1.68858,
              1.9879,
              2.3444
            ],
            [
              0.20785,
              1.0614,
              1.2341,
              1.44,
              1.6876,
              1.9875,
              2.3457
            ],
            [
              0.2369,
              1.0615,
              1.2332,
              1.4412,
              1.6889,
              1.9853,
              2.3438
            ],
            [
              0.2638,
              1.0674,
              1.2378,
              1.4407,
              1.6887,
              1.9854,
              2.3458
            ],
            [
              0.2932,
              1.082,
              1.2485,
              1.4485,
              1.6928,
              1.9856,
              2.3458
            ]
          ]
        },
        "timing_sense": "negative_unate"
      },
      {
        "cell_fall,delay_template13x7": {
          "index_1": [
            0.001,
            0.00617,
            0.01028,
            0.01851,
            0.03085,
            0.05553,
            0.09255,
            0.16659,
            0.27765,
            0.49977,
            0.83295,
            1.16647,
            1.5
          ],
          "index_2": [
            0.0,
            0.0096,
            0.01152,
            0.01382,
            0.01658,
            0.01989,
            0.02387
          ],
          "values": [
            [
              0.01465,
              0.05919,
              0.06789,
              0.07831,
              0.09079,
              0.10579,
              0.12376
            ],
            [
              0.01662,
              0.06113,
              0.06986,
              0.08027,
              0.09276,
              0.10772,
              0.12569
            ],
            [
              0.01825,
              0.06273,
              0.07145,
              0.08187,
              0.09436,
              0.10933,
              0.12732
            ],
            [
              0.02152,
              0.06594,
              0.07464,
              0.08507,
              0.09749,
              0.11245,
              0.13043
            ],
            [
              0.02651,
              0.0707,
              0.07942,
              0.08984,
              0.10222,
              0.11719,
              0.13518
            ],
            [
              0.03467,
              0.08039,
              0.08909,
              0.0995,
              0.11184,
              0.12682,
              0.14469
            ],
            [
              0.04344,
              0.09501,
              0.10357,
              0.11393,
              0.12638,
              0.14133,
              0.15926
            ],
            [
              0.05543,
              0.12351,
              0.1329,
              0.14338,
              0.15571,
              0.17056,
              0.18841
            ],
            [
              0.06686,
              0.15646,
              0.1687,
              0.1823,
              0.19739,
              0.21407,
              0.23256
            ],
            [
              0.07917,
              0.20355,
              0.22029,
              0.23836,
              0.25882,
              0.28131,
              0.30691
            ],
            [
              0.08471,
              0.25183,
              0.27413,
              0.2985,
              0.32538,
              0.35507,
              0.38788
            ],
            [
              0.08184,
              0.28624,
              0.31294,
              0.34234,
              0.37484,
              0.41044,
              0.44974
            ],
            [
              0.0735,
              0.3125,
              0.3434,
              0.3773,
              0.4147,
              0.4552,
              0.5003
            ]
          ]
        },
        "cell_rise,delay_template13x7": {
          "index_1": [
            0.001,
            0.00617,
            0.01028,
            0.01851,
            0.03085,
            0.05553,
            0.09255,
            0.16659,
            0.27765,
            0.49977,
            0.83295,
            1.16647,
            1.5
          ],
          "index_2": [
            0.0,
            0.0096,
            0.01152,
            0.01382,
            0.01658,
            0.01989,
            0.02387
          ],
          "values": [
            [
              0.21391,
              0.87724,
              1.00897,
              1.16857,
              1.35857,
              1.58607,
              1.85887
            ],
            [
              0.21003,
              0.87857,
              1.01086,
              1.16816,
              1.35976,
              1.58736,
              1.85986
            ],
            [
              0.20882,
              0.87928,
              1.01113,
              1.16933,
              1.36103,
              1.58893,
              1.86243
            ],
            [
              0.20869,
              0.88124,
              1.01347,
              1.17147,
              1.36318,
              1.59167,
              1.86567
            ],
            [
              0.21107,
              0.88353,
              1.01749,
              1.17629,
              1.36559,
              1.59569,
              1.87029
            ],
            [
              0.21932,
              0.89133,
              1.02442,
              1.18483,
              1.37583,
              1.60433,
              1.87713
            ],
            [
              0.23425,
              0.90468,
              1.03768,
              1.19827,
              1.38938,
              1.61798,
              1.89198
            ],
            [
              0.26471,
              0.93327,
              1.06618,
              1.22658,
              1.41778,
              1.64648,
              1.92087
            ],
            [
              0.31172,
              0.97852,
              1.11262,
              1.27153,
              1.46143,
              1.68993,
              1.96673
            ],
            [
              0.40408,
              1.07333,
              1.20613,
              1.36393,
              1.55452,
              1.78463,
              2.05973
            ],
            [
              0.52528,
              1.21498,
              1.34847,
              1.50688,
              1.69678,
              1.92688,
              2.20118
            ],
            [
              0.63344,
              1.35814,
              1.49134,
              1.64984,
              1.84144,
              2.07014,
              2.34364
            ],
            [
              0.731,
              1.5011,
              1.6343,
              1.7929,
              1.9846,
              2.2128,
              2.4866
            ]
          ]
        },
        "fall_transition,delay_template13x7": {
          "index_1": [
            0.001,
            0.00617,
            0.01028,
            0.01851,
            0.03085,
            0.05553,
            0.09255,
            0.16659,
            0.27765,
            0.49977,
            0.83295,
            1.16647,
            1.5
          ],
          "index_2": [
            0.0,
            0.0096,
            0.01152,
            0.01382,
            0.01658,
            0.01989,
            0.02387
          ],
          "values": [
            [
              0.01434,
              0.07145,
              0.08292,
              0.09667,
              0.11319,
              0.13297,
              0.15688
            ],
            [
              0.0142,
              0.07137,
              0.08294,
              0.09681,
              0.11327,
              0.13316,
              0.15699
            ],
            [
              0.01413,
              0.07148,
              0.08291,
              0.0967,
              0.11321,
              0.13301,
              0.15686
            ],
            [
              0.0141,
              0.07145,
              0.08286,
              0.0967,
              0.11322,
              0.1331,
              0.15699
            ],
            [
              0.01539,
              0.07144,
              0.08286,
              0.09668,
              0.1133,
              0.13303,
              0.15698
            ],
            [
              0.02014,
              0.0714,
              0.08293,
              0.09664,
              0.11326,
              0.13296,
              0.15696
            ],
            [
              0.02664,
              0.07395,
              0.08454,
              0.09749,
              0.11341,
              0.13314,
              0.15698
            ],
            [
              0.03762,
              0.08638,
              0.09532,
              0.10644,
              0.12059,
              0.13796,
              0.15992
            ],
            [
              0.05189,
              0.11227,
              0.12057,
              0.12983,
              0.14135,
              0.15623,
              0.1752
            ],
            [
              0.07678,
              0.15664,
              0.16758,
              0.18029,
              0.1937,
              0.20872,
              0.22512
            ],
            [
              0.11026,
              0.21258,
              0.22626,
              0.24179,
              0.25913,
              0.27783,
              0.29882
            ],
            [
              0.14114,
              0.2621,
              0.2784,
              0.2965,
              0.3167,
              0.3386,
              0.3633
            ],
            [
              0.1701,
              0.3075,
              0.3257,
              0.3461,
              0.3687,
              0.3946,
              0.4218
            ]
          ]
        },
        "related_pin": "C",
        "rise_transition,delay_template13x7": {
          "index_1": [
            0.001,
            0.00617,
            0.01028,
            0.01851,
            0.03085,
            0.05553,
            0.09255,
            0.16659,
            0.27765,
            0.49977,
            0.83295,
            1.16647,
            1.5
          ],
          "index_2": [
            0.0,
            0.0096,
            0.01152,
            0.01382,
            0.01658,
            0.01989,
            0.02387
          ],
          "values": [
            [
              0.19529,
              1.06099,
              1.23301,
              1.44023,
              1.68991,
              1.98742,
              2.34448
            ],
            [
              0.19529,
              1.0613,
              1.23447,
              1.44018,
              1.68996,
              1.98745,
              2.34412
            ],
            [
              0.19528,
              1.06156,
              1.23368,
              1.43971,
              1.68928,
              1.98787,
              2.34502
            ],
            [
              0.19514,
              1.06097,
              1.23396,
              1.44023,
              1.68901,
              1.98758,
              2.34565
            ],
            [
              0.19505,
              1.06023,
              1.23379,
              1.44147,
              1.68844,
              1.98592,
              2.34594
            ],
            [
              0.19511,
              1.06077,
              1.23288,
              1.44024,
              1.68995,
              1.98789,
              2.34397
            ],
            [
              0.19509,
              1.06093,
              1.23298,
              1.44029,
              1.68992,
              1.98758,
              2.34482
            ],
            [
              0.19534,
              1.06099,
              1.23307,
              1.43981,
              1.68978,
              1.98754,
              2.34486
            ],
            [
              0.1968,
              1.06036,
              1.23391,
              1.44137,
              1.68867,
              1.985,
              2.346
            ],
            [
              0.21419,
              1.0614,
              1.2345,
              1.44,
              1.688,
              1.9867,
              2.3461
            ],
            [
              0.2542,
              1.0615,
              1.2341,
              1.4405,
              1.688,
              1.9867,
              2.3452
            ],
            [
              0.293,
              1.0675,
              1.2368,
              1.4405,
              1.6882,
              1.9877,
              2.3442
            ],
            [
              0.3323,
              1.086,
              1.2489,
              1.4481,
              1.6914,
              1.9865,
              2.3429
            ]
          ]
        },
        "timing_sense": "negative_unate"
      },
      {
        "cell_fall,delay_template13x7": {
          "index_1": [
            0.001,
            0.00617,
            0.01028,
            0.01851,
            0.03085,
            0.05553,
            0.09255,
            0.16659,
            0.27765,
            0.49977,
            0.83295,
            1.16647,
            1.5
          ],
          "index_2": [
            0.0,
            0.0096,
            0.01152,
            0.01382,
            0.01658,
            0.01989,
            0.02387
          ],
          "values": [
            [
              0.01262,
              0.05687,
              0.06581,
              0.0764,
              0.08897,
              0.10412,
              0.12246
            ],
            [
              0.01465,
              0.05901,
              0.06788,
              0.07848,
              0.09108,
              0.10628,
              0.12464
            ],
            [
              0.01629,
              0.06069,
              0.06953,
              0.08,
              0.09277,
              0.10789,
              0.12631
            ],
            [
              0.01953,
              0.06391,
              0.07269,
              0.08328,
              0.09592,
              0.11123,
              0.1294
            ],
            [
              0.02432,
              0.06886,
              0.07762,
              0.08822,
              0.10087,
              0.11607,
              0.13439
            ],
            [
              0.03148,
              0.07873,
              0.08754,
              0.09803,
              0.11063,
              0.12596,
              0.14416
            ],
            [
              0.03923,
              0.09359,
              0.10236,
              0.11291,
              0.12549,
              0.14078,
              0.15871
            ],
            [
              0.04963,
              0.12244,
              0.13207,
              0.14278,
              0.1553,
              0.17039,
              0.18862
            ],
            [
              0.05953,
              0.1559,
              0.16848,
              0.18236,
              0.19773,
              0.21469,
              0.23347
            ],
            [
              0.06953,
              0.20419,
              0.22142,
              0.24038,
              0.26127,
              0.28427,
              0.30968
            ],
            [
              0.07286,
              0.25482,
              0.27766,
              0.30274,
              0.33027,
              0.36047,
              0.39377
            ],
            [
              0.06854,
              0.29174,
              0.31944,
              0.34974,
              0.38294,
              0.41924,
              0.45914
            ],
            [
              0.0594,
              0.3202,
              0.3522,
              0.3872,
              0.4255,
              0.4673,
              0.5131
            ]
          ]
        },
        "cell_rise,delay_template13x7": {
          "index_1": [
            0.001,
            0.00617,
            0.01028,
            0.01851,
            0.03085,
            0.05553,
            0.09255,
            0.16659,
            0.27765,
            0.49977,
            0.83295,
            1.16647,
            1.5
          ],
          "index_2": [
            0.0,
            0.0096,
            0.01152,
            0.01382,
            0.01658,
            0.01989,
            0.02387
          ],
          "values": [
            [
              0.16203,
              0.82552,
              0.95734,
              1.11487,
              1.30617,
              1.53447,
              1.80817
            ],
            [
              0.15732,
              0.82595,
              0.95792,
              1.11566,
              1.30716,
              1.53546,
              1.80906
            ],
            [
              0.15606,
              0.82581,
              0.9591,
              1.11813,
              1.30833,
              1.53553,
              1.80873
            ],
            [
              0.15538,
              0.82808,
              0.96013,
              1.11977,
              1.31068,
              1.53897,
              1.81248
            ],
            [
              0.15687,
              0.83027,
              0.96381,
              1.12329,
              1.31409,
              1.54209,
              1.81519
            ],
            [
              0.16357,
              0.83793,
              0.97062,
              1.12922,
              1.32142,
              1.55062,
              1.82502
            ],
            [
              0.1768,
              0.84954,
              0.98308,
              1.14208,
              1.33218,
              1.56258,
              1.83808
            ],
            [
              0.20589,
              0.87567,
              1.00838,
              1.16738,
              1.35977,
              1.58918,
              1.86367
            ],
            [
              0.2521,
              0.91863,
              1.05163,
              1.21022,
              1.40062,
              1.63102,
              1.90633
            ],
            [
              0.34282,
              1.00633,
              1.13983,
              1.29903,
              1.48962,
              1.71683,
              1.99343
            ],
            [
              0.45217,
              1.14318,
              1.27488,
              1.43298,
              1.62408,
              1.85138,
              2.12737
            ],
            [
              0.54484,
              1.28024,
              1.41234,
              1.57064,
              1.76074,
              1.98714,
              2.26304
            ],
            [
              0.627,
              1.4193,
              1.5508,
              1.7088,
              1.8984,
              2.1243,
              2.3996
            ]
          ]
        },
        "fall_transition,delay_template13x7": {
          "index_1": [
            0.001,
            0.00617,
            0.01028,
            0.01851,
            0.03085,
            0.05553,
            0.09255,
            0.16659,
            0.27765,
            0.49977,
            0.83295,
            1.16647,
            1.5
          ],
          "index_2": [
            0.0,
            0.0096,
            0.01152,
            0.01382,
            0.01658,
            0.01989,
            0.02387
          ],
          "values": [
            [
              0.01186,
              0.07062,
              0.08247,
              0.09622,
              0.11313,
              0.13325,
              0.15768
            ],
            [
              0.01184,
              0.07056,
              0.0824,
              0.09644,
              0.11307,
              0.13322,
              0.15793
            ],
            [
              0.01185,
              0.07063,
              0.08231,
              0.09646,
              0.11336,
              0.13357,
              0.15808
            ],
            [
              0.01214,
              0.07062,
              0.08238,
              0.09638,
              0.11329,
              0.13362,
              0.15793
            ],
            [
              0.01392,
              0.0706,
              0.08228,
              0.09637,
              0.11327,
              0.13365,
              0.15803
            ],
            [
              0.0191,
              0.07056,
              0.08233,
              0.09647,
              0.11332,
              0.13366,
              0.1579
            ],
            [
              0.02565,
              0.07324,
              0.08405,
              0.09718,
              0.11358,
              0.13352,
              0.15803
            ],
            [
              0.03706,
              0.08591,
              0.09494,
              0.10632,
              0.12052,
              0.13837,
              0.16073
            ],
            [
              0.05182,
              0.11192,
              0.12024,
              0.12949,
              0.14122,
              0.15632,
              0.17563
            ],
            [
              0.07826,
              0.15663,
              0.16758,
              0.17977,
              0.19331,
              0.20856,
              0.22502
            ],
            [
              0.11384,
              0.21324,
              0.22682,
              0.24226,
              0.25938,
              0.27843,
              0.29951
            ],
            [
              0.14663,
              0.2632,
              0.2795,
              0.2976,
              0.3172,
              0.3395,
              0.3642
            ],
            [
              0.1775,
              0.3098,
              0.328,
              0.3482,
              0.3703,
              0.3952,
              0.4231
            ]
          ]
        },
        "related_pin": "D",
        "rise_transition,delay_template13x7": {
          "index_1": [
            0.001,
            0.00617,
            0.01028,
            0.01851,
            0.03085,
            0.05553,
            0.09255,
            0.16659,
            0.27765,
            0.49977,
            0.83295,
            1.16647,
            1.5
          ],
          "index_2": [
            0.0,
            0.0096,
            0.01152,
            0.01382,
            0.01658,
            0.01989,
            0.02387
          ],
          "values": [
            [
              0.19488,
              1.06148,
              1.23398,
              1.44025,
              1.68828,
              1.9875,
              2.34581
            ],
            [
              0.19505,
              1.06143,
              1.23393,
              1.44022,
              1.68848,
              1.98766,
              2.34533
            ],
            [
              0.19473,
              1.06079,
              1.23374,
              1.44045,
              1.68975,
              1.98639,
              2.3433
            ],
            [
              0.19461,
              1.06125,
              1.23347,
              1.44071,
              1.68864,
              1.98759,
              2.3447
            ],
            [
              0.19443,
              1.0608,
              1.23416,
              1.43964,
              1.68962,
              1.98706,
              2.34375
            ],
            [
              0.19369,
              1.06136,
              1.23384,
              1.44012,
              1.68889,
              1.9871,
              2.34597
            ],
            [
              0.19255,
              1.061,
              1.23411,
              1.4409,
              1.68825,
              1.9865,
              2.34595
            ],
            [
              0.18924,
              1.06156,
              1.23379,
              1.4402,
              1.68821,
              1.9875,
              2.34499
            ],
            [
              0.19548,
              1.06083,
              1.23438,
              1.44077,
              1.6883,
              1.98596,
              2.3459
            ],
            [
              0.22685,
              1.06052,
              1.23357,
              1.4413,
              1.6887,
              1.9857,
              2.3446
            ],
            [
              0.27856,
              1.0603,
              1.2331,
              1.4399,
              1.6895,
              1.9862,
              2.344
            ],
            [
              0.3266,
              1.0734,
              1.2383,
              1.441,
              1.6891,
              1.9857,
              2.3443
            ],
            [
              0.3717,
              1.1015,
              1.2592,
              1.4533,
              1.6934,
              1.9854,
              2.3458
            ]
          ]
        },
        "timing_sense": "negative_unate"
      }
    ]
  }
}